Metadata-Version: 1.1
Name: haproxy-herald
Version: 0.1.0
Summary: Haproxy load feedback and check agent
Home-page: https://github.com/helpshift/herald
Author: Raghu Udiyar
Author-email: raghusiddarth@gmail.com
License: MIT
Download-URL: https://github.com/helpshift/herald/tarball/0.1.0
Keywords: Haproxy
Platform: UNKNOWN
